{"title":"Singh vs Kaur (2013) - Punjabi - 1CD - HDRip - x264 -MP3 -={SPAR","uid":12069488,"size":730885747,"categoryP":"video","categoryS":"movies","magnet":"?xt=urn:btih:001994ec1dd64e82c243e6f34a1ca91566270786&amp;dn=Singh+vs+Kaur+%282013%29+-+Punjabi+-+1CD+-+HDRip+-+x264+-MP3+-%3D%7BSPAR&amp;tr=udp%3A%2F%2Ftracker.openbittorrent.com%3A80&amp;tr=udp%3A%2F%2Fopen.demonii.com%3A1337&amp;tr=udp%3A%2F%2Ftracker.coppersurfer.tk%3A6969&amp;tr=udp%3A%2F%2Fexodus.desync.com%3A6969","seeders":3,"leechers":1,"uploader":"SS132203","files":2,"time":1435477855,"description":"Singh vs Kaur (2013) - Punjabi - 1CD - HDRip - x264 -MP3 -={SPARROW}=-\n &lt;a href=&quot;\nhttp://imgsparrow.co/image/YW&quot; rel=&quot;nofollow&quot; target=&quot;_NEW&quot;&gt;\nhttp://imgsparrow.co/image/YW&lt;/a&gt;\n &lt;a href=&quot;\nhttp://imgsparrow.co/image/9b&quot; rel=&quot;nofollow&quot; target=&quot;_NEW&quot;&gt;\nhttp://imgsparrow.co/image/9b&lt;/a&gt;\n\nInfo : - \n &lt;a href=&quot;\nhttp://imgsparrow.co/image/cJ&quot; rel=&quot;nofollow&quot; target=&quot;_NEW&quot;&gt;\nhttp://imgsparrow.co/image/cJ&lt;/a&gt;\n\nScreens : - \n &lt;a href=&quot;\nhttp://imgsparrow.co/image/YB&quot; rel=&quot;nofollow&quot; target=&quot;_NEW&quot;&gt;\nhttp://imgsparrow.co/image/YB&lt;/a&gt; &lt;a href=&quot;\nhttp://imgsparrow.co/image/YK&quot; rel=&quot;nofollow&quot; target=&quot;_NEW&quot;&gt;\nhttp://imgsparrow.co/image/YK&lt;/a&gt; &lt;a href=&quot;\nhttp://imgsparrow.co/image/Y2&quot; rel=&quot;nofollow&quot; target=&quot;_NEW&quot;&gt;\nhttp://imgsparrow.co/image/Y2&lt;/a&gt; &lt;a href=&quot;\nhttp://imgsparrow.co/image/Y3&quot; rel=&quot;nofollow&quot; target=&quot;_NEW&quot;&gt;\nhttp://imgsparrow.co/image/Y3&lt;/a&gt; &lt;a href=&quot;\nhttp://imgsparrow.co/image/Yi&quot; rel=&quot;nofollow&quot; target=&quot;_NEW&quot;&gt;\nhttp://imgsparrow.co/image/Yi&lt;/a&gt; &lt;a href=&quot;\nhttp://imgsparrow.co/image/YV&quot; rel=&quot;nofollow&quot; target=&quot;_NEW&quot;&gt;\nhttp://imgsparrow.co/image/YV&lt;/a&gt; &lt;a href=&quot;\nhttp://imgsparrow.co/image/Yl&quot; rel=&quot;nofollow&quot; target=&quot;_NEW&quot;&gt;\nhttp://imgsparrow.co/image/Yl&lt;/a&gt; &lt;a href=&quot;\nhttp://imgsparrow.co/image/Ys&quot; rel=&quot;nofollow&quot; target=&quot;_NEW&quot;&gt;\nhttp://imgsparrow.co/image/Ys&lt;/a&gt; &lt;a href=&quot;\nhttp://imgsparrow.co/image/YS&quot; rel=&quot;nofollow&quot; target=&quot;_NEW&quot;&gt;\nhttp://imgsparrow.co/image/YS&lt;/a&gt; &lt;a href=&quot;\nhttp://imgsparrow.co/image/YR&quot; rel=&quot;nofollow&quot; target=&quot;_NEW&quot;&gt;\nhttp://imgsparrow.co/image/YR&lt;/a&gt;\n &lt;a href=&quot;\nhttp://imgsparrow.co/image/N2&quot; rel=&quot;nofollow&quot; target=&quot;_NEW&quot;&gt;\nhttp://imgsparrow.co/image/N2&lt;/a&gt;","torrent":{"xt":"urn:btih:001994ec1dd64e82c243e6f34a1ca91566270786","amp;dn":"Singh+vs+Kaur+%282013%29+-+Punjabi+-+1CD+-+HDRip+-+x264+-MP3+-%3D%7BSPAR","amp;tr":["udp%3A%2F%2Ftracker.openbittorrent.com%3A80","udp%3A%2F%2Fopen.demonii.com%3A1337","udp%3A%2F%2Ftracker.coppersurfer.tk%3A6969","udp%3A%2F%2Fexodus.desync.com%3A6969"],"infoHash":"001994ec1dd64e82c243e6f34a1ca91566270786","infoHashBuffer":{"type":"Buffer","data":[0,25,148,236,29,214,78,130,194,67,230,243,74,28,169,21,102,39,7,134]},"announce":[],"urlList":[]}}