{"title":"April Blue - Perfect Gonzo","uid":9331354,"size":900474101,"categoryP":"porn","categoryS":"movie_clips","magnet":"?xt=urn:btih:024c444cbe73dddca2bcd6d1f3b8fcf4a58040a9&amp;dn=April+Blue+-+Perfect+Gonzo&amp;tr=udp%3A%2F%2Ftracker.openbittorrent.com%3A80&amp;tr=udp%3A%2F%2Fopen.demonii.com%3A1337&amp;tr=udp%3A%2F%2Ftracker.coppersurfer.tk%3A6969&amp;tr=udp%3A%2F%2Fexodus.desync.com%3A6969","seeders":3,"leechers":4,"uploader":"homepablo","files":1,"time":1386776208,"description":"Screen:\n &lt;a href=&quot;\nhttp://imgpolo.biz/share-970A_52A87761.html&quot; rel=&quot;nofollow&quot; target=&quot;_NEW&quot;&gt;\nhttp://imgpolo.biz/share-970A_52A87761.html&lt;/a&gt;\n &lt;a href=&quot;\nhttp://imgpolo.biz/share-BC9C_52A87761.html&quot; rel=&quot;nofollow&quot; target=&quot;_NEW&quot;&gt;\nhttp://imgpolo.biz/share-BC9C_52A87761.html&lt;/a&gt;\n\nSize: 858 Mb\n\nDownload, Seed &amp; Enjoy :)","torrent":{"xt":"urn:btih:024c444cbe73dddca2bcd6d1f3b8fcf4a58040a9","amp;dn":"April+Blue+-+Perfect+Gonzo","amp;tr":["udp%3A%2F%2Ftracker.openbittorrent.com%3A80","udp%3A%2F%2Fopen.demonii.com%3A1337","udp%3A%2F%2Ftracker.coppersurfer.tk%3A6969","udp%3A%2F%2Fexodus.desync.com%3A6969"],"infoHash":"024c444cbe73dddca2bcd6d1f3b8fcf4a58040a9","infoHashBuffer":{"type":"Buffer","data":[2,76,68,76,190,115,221,220,162,188,214,209,243,184,252,244,165,128,64,169]},"announce":[],"urlList":[]}}