{"title":"Yokihi.aka.Princess.Yang.Kwei-fei.1955.720p.BluRay.x264-PublicHD","uid":9172637,"size":4695685969,"categoryP":"video","categoryS":"hd___movies","magnet":"?xt=urn:btih:088956c245c9d8f08f26b654b5cf1a9de0820089&amp;dn=Yokihi.aka.Princess.Yang.Kwei-fei.1955.720p.BluRay.x264-PublicHD&amp;tr=udp%3A%2F%2Ftracker.openbittorrent.com%3A80&amp;tr=udp%3A%2F%2Fopen.demonii.com%3A1337&amp;tr=udp%3A%2F%2Ftracker.coppersurfer.tk%3A6969&amp;tr=udp%3A%2F%2Fexodus.desync.com%3A6969","seeders":3,"leechers":5,"uploader":"aoloffline","files":2,"time":1384096022,"description":"                PublicHD - High-Definition Bittorrent Community\n      \n                           \n    \n              ----------------------------------------------------\n\nYokihi.aka.Princess.Yang.Kwei-fei.1955.720p.BluRay.x264-PublicHD\n &lt;a href=&quot;\nhttp://www.imdb.com/title/tt0048820/&quot; rel=&quot;nofollow&quot; target=&quot;_NEW&quot;&gt;\nhttp://www.imdb.com/title/tt0048820/&lt;/a&gt;\n\nDate ...............: November 10 2013\nRuntime ............: 1:31:11\nSize ...............: 4.37 GB\nVideo ..............: 960x720\nBitrate ............: ~6089 kbps (x264 &lt;a class=&quot;__cf_email__&quot; href=&quot;/cdn-cgi/l/email-protection&quot; data-cfemail=&quot;2a62434d426a661e041b&quot;&gt;[email&amp;#160;protected]&lt;/a&gt;&lt;script cf-hash='f9e31' type=&quot;text/javascript&quot;&gt;\n/* &lt;![CDATA[ */!function(){try{var t=&quot;currentScript&quot;in document?document.currentScript:function(){for(var t=document.getElementsByTagName(&quot;script&quot;),e=t.length;e--;)if(t[e].getAttribute(&quot;cf-hash&quot;))return t[e]}();if(t&amp;&amp;t.previousSibling){var e,r,n,i,c=t.previousSibling,a=c.getAttribute(&quot;data-cfemail&quot;);if(a){for(e=&quot;&quot;,r=parseInt(a.substr(0,2),16),n=2;a.length-n;n+=2)i=parseInt(a.substr(n,2),16)^r,e+=String.fromCharCode(i);e=document.createTextNode(e),c.parentNode.replaceChild(e,c)}}}catch(u){}}();/* ]]&gt; */&lt;/script&gt;)\nAudio 1.............: Japanese DD2.0 Ch 640 kbps\nChapters............: Yes\nSource .............: 1080p Blu-ray AVC LPCM 2.0-insinuendo\nSubs ...............: English\n\nScreens.............: Opening Week - 1956\nGenre ..............: Drama | History | Romance\n\n\nSCREENS\n &lt;a href=&quot;\nhttp://someimage.com/49pQDXH&quot; rel=&quot;nofollow&quot; target=&quot;_NEW&quot;&gt;\nhttp://someimage.com/49pQDXH&lt;/a&gt;\n &lt;a href=&quot;\nhttp://someimage.com/3X3o95J&quot; rel=&quot;nofollow&quot; target=&quot;_NEW&quot;&gt;\nhttp://someimage.com/3X3o95J&lt;/a&gt;\n &lt;a href=&quot;\nhttp://someimage.com/djEepmI&quot; rel=&quot;nofollow&quot; target=&quot;_NEW&quot;&gt;\nhttp://someimage.com/djEepmI&lt;/a&gt;\n &lt;a href=&quot;\nhttp://someimage.com/coSu9Ro&quot; rel=&quot;nofollow&quot; target=&quot;_NEW&quot;&gt;\nhttp://someimage.com/coSu9Ro&lt;/a&gt;\n &lt;a href=&quot;\nhttp://someimage.com/864CUBD&quot; rel=&quot;nofollow&quot; target=&quot;_NEW&quot;&gt;\nhttp://someimage.com/864CUBD&lt;/a&gt;\n &lt;a href=&quot;\nhttp://someimage.com/SWFMJz0&quot; rel=&quot;nofollow&quot; target=&quot;_NEW&quot;&gt;\nhttp://someimage.com/SWFMJz0&lt;/a&gt;\n &lt;a href=&quot;\nhttp://someimage.com/JvAME5R&quot; rel=&quot;nofollow&quot; target=&quot;_NEW&quot;&gt;\nhttp://someimage.com/JvAME5R&lt;/a&gt;\n &lt;a href=&quot;\nhttp://someimage.com/TipWw8g&quot; rel=&quot;nofollow&quot; target=&quot;_NEW&quot;&gt;\nhttp://someimage.com/TipWw8g&lt;/a&gt;\n &lt;a href=&quot;\nhttp://someimage.com/wPuvMoX&quot; rel=&quot;nofollow&quot; target=&quot;_NEW&quot;&gt;\nhttp://someimage.com/wPuvMoX&lt;/a&gt;\n &lt;a href=&quot;\nhttp://someimage.com/wQqeCWQ&quot; rel=&quot;nofollow&quot; target=&quot;_NEW&quot;&gt;\nhttp://someimage.com/wQqeCWQ&lt;/a&gt;\n","torrent":{"xt":"urn:btih:088956c245c9d8f08f26b654b5cf1a9de0820089","amp;dn":"Yokihi.aka.Princess.Yang.Kwei-fei.1955.720p.BluRay.x264-PublicHD","amp;tr":["udp%3A%2F%2Ftracker.openbittorrent.com%3A80","udp%3A%2F%2Fopen.demonii.com%3A1337","udp%3A%2F%2Ftracker.coppersurfer.tk%3A6969","udp%3A%2F%2Fexodus.desync.com%3A6969"],"infoHash":"088956c245c9d8f08f26b654b5cf1a9de0820089","infoHashBuffer":{"type":"Buffer","data":[8,137,86,194,69,201,216,240,143,38,182,84,181,207,26,157,224,130,0,137]},"announce":[],"urlList":[]}}