{"title":"Pulp - Hits [EAC-FLAC]","uid":4829819,"size":540001068,"categoryP":"audio","categoryS":"flac","magnet":"?xt=urn:btih:0af53673d021e26fe3d2d3f152159f74dba51937&amp;dn=Pulp+-+Hits+%5BEAC-FLAC%5D&amp;tr=udp%3A%2F%2Ftracker.openbittorrent.com%3A80&amp;tr=udp%3A%2F%2Fopen.demonii.com%3A1337&amp;tr=udp%3A%2F%2Ftracker.coppersurfer.tk%3A6969&amp;tr=udp%3A%2F%2Fexodus.desync.com%3A6969","seeders":3,"leechers":0,"uploader":"ddirt80","files":17,"time":1239088999,"description":"Enjoy","torrent":{"xt":"urn:btih:0af53673d021e26fe3d2d3f152159f74dba51937","amp;dn":"Pulp+-+Hits+%5BEAC-FLAC%5D","amp;tr":["udp%3A%2F%2Ftracker.openbittorrent.com%3A80","udp%3A%2F%2Fopen.demonii.com%3A1337","udp%3A%2F%2Ftracker.coppersurfer.tk%3A6969","udp%3A%2F%2Fexodus.desync.com%3A6969"],"infoHash":"0af53673d021e26fe3d2d3f152159f74dba51937","infoHashBuffer":{"type":"Buffer","data":[10,245,54,115,208,33,226,111,227,210,211,241,82,21,159,116,219,165,25,55]},"announce":[],"urlList":[]}}