{"title":"TuneIn Radio Pro v12.8 Build 183 Android","uid":11310468,"size":19237574,"categoryP":"applications","categoryS":"android","magnet":"?xt=urn:btih:124a4720662c064f0980ea838117b22cafd80f68&amp;dn=TuneIn+Radio+Pro+v12.8+Build+183+Android&amp;tr=udp%3A%2F%2Ftracker.openbittorrent.com%3A80&amp;tr=udp%3A%2F%2Fopen.demonii.com%3A1337&amp;tr=udp%3A%2F%2Ftracker.coppersurfer.tk%3A6969&amp;tr=udp%3A%2F%2Fexodus.desync.com%3A6969","seeders":3,"leechers":0,"uploader":".BONE.","files":-1,"time":1414508881,"description":"What's New\n+ Added a rewind/fast forward button\n+ Streamlined mini-player in the rest of the app\n+ Hold and resume your position in podcasts and on-demand content\n+ Car Mode UI fixes &amp; improvements\n+ Echo improvements &amp; icon change\n+ Rename your recordings\n+ Delete multiple recordings at once\n\nThis app has no advertisements","torrent":{"xt":"urn:btih:124a4720662c064f0980ea838117b22cafd80f68","amp;dn":"TuneIn+Radio+Pro+v12.8+Build+183+Android","amp;tr":["udp%3A%2F%2Ftracker.openbittorrent.com%3A80","udp%3A%2F%2Fopen.demonii.com%3A1337","udp%3A%2F%2Ftracker.coppersurfer.tk%3A6969","udp%3A%2F%2Fexodus.desync.com%3A6969"],"infoHash":"124a4720662c064f0980ea838117b22cafd80f68","infoHashBuffer":{"type":"Buffer","data":[18,74,71,32,102,44,6,79,9,128,234,131,129,23,178,44,175,216,15,104]},"announce":[],"urlList":[]}}