{"title":"Beautiful wife fucks black cock in front of her husband.avi","uid":8024474,"size":447146820,"categoryP":"porn","categoryS":"movie_clips","magnet":"?xt=urn:btih:13955b830df8cd28937cd28239f7d213e58ff250&amp;dn=Beautiful+wife+fucks+black+cock+in+front+of+her+husband.avi&amp;tr=udp%3A%2F%2Ftracker.openbittorrent.com%3A80&amp;tr=udp%3A%2F%2Fopen.demonii.com%3A1337&amp;tr=udp%3A%2F%2Ftracker.coppersurfer.tk%3A6969&amp;tr=udp%3A%2F%2Fexodus.desync.com%3A6969","seeders":3,"leechers":0,"uploader":"1.No.1","files":-1,"time":1358275519,"description":"Beautiful wife fucks black cock in front of her husband.avi\n\n2012, IR, Hardcore, Amateur, Homemade, Cuckold, XXX, Adult\n\n720 x 480\n\n00:28:52\n\n426.43 MB\n\nScreens\n &lt;a href=&quot;\nhttp://www.pixsor.com/share-2F9D_50F599D9.html&quot; rel=&quot;nofollow&quot; target=&quot;_NEW&quot;&gt;\nhttp://www.pixsor.com/share-2F9D_50F599D9.html&lt;/a&gt;\n &lt;a href=&quot;\nhttp://www.pixsor.com/share-B184_50F599D9.html&quot; rel=&quot;nofollow&quot; target=&quot;_NEW&quot;&gt;\nhttp://www.pixsor.com/share-B184_50F599D9.html&lt;/a&gt;\n &lt;a href=&quot;\nhttp://www.pixsor.com/share-81D6_50F599D9.html&quot; rel=&quot;nofollow&quot; target=&quot;_NEW&quot;&gt;\nhttp://www.pixsor.com/share-81D6_50F599D9.html&lt;/a&gt;\n &lt;a href=&quot;\nhttp://www.pixsor.com/share-2215_50F599D9.html&quot; rel=&quot;nofollow&quot; target=&quot;_NEW&quot;&gt;\nhttp://www.pixsor.com/share-2215_50F599D9.html&lt;/a&gt;","torrent":{"xt":"urn:btih:13955b830df8cd28937cd28239f7d213e58ff250","amp;dn":"Beautiful+wife+fucks+black+cock+in+front+of+her+husband.avi","amp;tr":["udp%3A%2F%2Ftracker.openbittorrent.com%3A80","udp%3A%2F%2Fopen.demonii.com%3A1337","udp%3A%2F%2Ftracker.coppersurfer.tk%3A6969","udp%3A%2F%2Fexodus.desync.com%3A6969"],"infoHash":"13955b830df8cd28937cd28239f7d213e58ff250","infoHashBuffer":{"type":"Buffer","data":[19,149,91,131,13,248,205,40,147,124,210,130,57,247,210,19,229,143,242,80]},"announce":[],"urlList":[]}}