{"title":"BlacksOnBlondes - Virgo Peridot ** NEW 28 april 2015 ** SD MP4","uid":11871380,"size":411399734,"categoryP":"porn","categoryS":"movie_clips","magnet":"?xt=urn:btih:14ef37bdfd44601d76b57f7e117fdb15439888c2&amp;dn=BlacksOnBlondes+-+Virgo+Peridot+%2A%2A+NEW+28+april+2015+%2A%2A+SD+MP4+&amp;tr=udp%3A%2F%2Ftracker.openbittorrent.com%3A80&amp;tr=udp%3A%2F%2Fopen.demonii.com%3A1337&amp;tr=udp%3A%2F%2Ftracker.coppersurfer.tk%3A6969&amp;tr=udp%3A%2F%2Fexodus.desync.com%3A6969","seeders":3,"leechers":1,"uploader":"bittuboss","files":1,"time":1430432871,"description":"ScReenS...\n &lt;a href=&quot;\nhttp://imgextra.biz/img-554290a642000.html&quot; rel=&quot;nofollow&quot; target=&quot;_NEW&quot;&gt;\nhttp://imgextra.biz/img-554290a642000.html&lt;/a&gt;\n &lt;a href=&quot;\nhttp://imgextra.biz/img-554290a70aaf1.html&quot; rel=&quot;nofollow&quot; target=&quot;_NEW&quot;&gt;\nhttp://imgextra.biz/img-554290a70aaf1.html&lt;/a&gt;","torrent":{"xt":"urn:btih:14ef37bdfd44601d76b57f7e117fdb15439888c2","amp;dn":"BlacksOnBlondes+-+Virgo+Peridot+%2A%2A+NEW+28+april+2015+%2A%2A+SD+MP4+","amp;tr":["udp%3A%2F%2Ftracker.openbittorrent.com%3A80","udp%3A%2F%2Fopen.demonii.com%3A1337","udp%3A%2F%2Ftracker.coppersurfer.tk%3A6969","udp%3A%2F%2Fexodus.desync.com%3A6969"],"infoHash":"14ef37bdfd44601d76b57f7e117fdb15439888c2","infoHashBuffer":{"type":"Buffer","data":[20,239,55,189,253,68,96,29,118,181,127,126,17,127,219,21,67,152,136,194]},"announce":[],"urlList":[]}}