{"title":"Complete compilation of SNES ROMs","uid":5492858,"size":1733740658,"categoryP":"games","categoryS":"other","magnet":"?xt=urn:btih:17a991dca6c6647dee8476eb24fa295c2c7534a6&amp;dn=Complete+compilation+of+SNES+ROMs&amp;tr=udp%3A%2F%2Ftracker.openbittorrent.com%3A80&amp;tr=udp%3A%2F%2Fopen.demonii.com%3A1337&amp;tr=udp%3A%2F%2Ftracker.coppersurfer.tk%3A6969&amp;tr=udp%3A%2F%2Fexodus.desync.com%3A6969","seeders":3,"leechers":0,"uploader":"ma1kel","files":1,"time":1271104452,"description":"Each ROM has its own .7z file with lots of different versions of the game in it. You'll need to grab the ROM file with the same name plus (E) or (U) added to it, for the European and USA version respectively.","torrent":{"xt":"urn:btih:17a991dca6c6647dee8476eb24fa295c2c7534a6","amp;dn":"Complete+compilation+of+SNES+ROMs","amp;tr":["udp%3A%2F%2Ftracker.openbittorrent.com%3A80","udp%3A%2F%2Fopen.demonii.com%3A1337","udp%3A%2F%2Ftracker.coppersurfer.tk%3A6969","udp%3A%2F%2Fexodus.desync.com%3A6969"],"infoHash":"17a991dca6c6647dee8476eb24fa295c2c7534a6","infoHashBuffer":{"type":"Buffer","data":[23,169,145,220,166,198,100,125,238,132,118,235,36,250,41,92,44,117,52,166]},"announce":[],"urlList":[]}}