{"title":"All.Cheerleaders.Die.2013.BRRip.XviD.MP3-RARBG","uid":10567269,"size":1176129700,"categoryP":"video","categoryS":"movies","magnet":"?xt=urn:btih:17c6e9ffdab40e2b75b4858dafad51d8b885f229&amp;dn=All.Cheerleaders.Die.2013.BRRip.XviD.MP3-RARBG&amp;tr=udp%3A%2F%2Ftracker.openbittorrent.com%3A80&amp;tr=udp%3A%2F%2Fopen.demonii.com%3A1337&amp;tr=udp%3A%2F%2Ftracker.coppersurfer.tk%3A6969&amp;tr=udp%3A%2F%2Fexodus.desync.com%3A6969","seeders":3,"leechers":1,"uploader":"Drarbg","files":4,"time":1405539454,"description":" &lt;a href=&quot;https://rarbg.com&quot; rel=&quot;nofollow&quot; target=&quot;_NEW&quot;&gt;https://rarbg.com&lt;/a&gt;\n\nAll.Cheerleaders.Die.2013.BRRip.XviD.MP3-RARBG\n\nAuto IMDB: &lt;a href=&quot;\nhttp://www.imdb.com/title/tt2527186/&quot; rel=&quot;nofollow&quot; target=&quot;_NEW&quot;&gt;\nhttp://www.imdb.com/title/tt2527186/&lt;/a&gt;\n\n-----------------------------------------\nScreens : &lt;a href=&quot;\nhttp://i.imgur.com/wHtbiFV.png&quot; rel=&quot;nofollow&quot; target=&quot;_NEW&quot;&gt;\nhttp://i.imgur.com/wHtbiFV.png&lt;/a&gt; &lt;a href=&quot;\nhttp://i.imgur.com/Nnn8YgK.png&quot; rel=&quot;nofollow&quot; target=&quot;_NEW&quot;&gt;\nhttp://i.imgur.com/Nnn8YgK.png&lt;/a&gt; &lt;a href=&quot;\nhttp://i.imgur.com/jUtQuJO.png&quot; rel=&quot;nofollow&quot; target=&quot;_NEW&quot;&gt;\nhttp://i.imgur.com/jUtQuJO.png&lt;/a&gt; &lt;a href=&quot;\nhttp://i.imgur.com/jcPeOSb.png&quot; rel=&quot;nofollow&quot; target=&quot;_NEW&quot;&gt;\nhttp://i.imgur.com/jcPeOSb.png&lt;/a&gt; &lt;a href=&quot;\nhttp://i.imgur.com/G98h7hT.png&quot; rel=&quot;nofollow&quot; target=&quot;_NEW&quot;&gt;\nhttp://i.imgur.com/G98h7hT.png&lt;/a&gt; &lt;a href=&quot;\nhttp://i.imgur.com/z3ryMHw.png&quot; rel=&quot;nofollow&quot; target=&quot;_NEW&quot;&gt;\nhttp://i.imgur.com/z3ryMHw.png&lt;/a&gt;\n\n-----------------------------------------\nAuto Media Info :\nVideo Format........: MPEG-4 Visual\nCodec ID............: XVID\nCodec ID/Hint.......: XviD\nLength..............: 1h29mn\nVideo...............: 720x300 ( 23.976fps )\nBitrate.............: 1545Kbps\nAudio Format........: MPEG Audio\nCodec ID............: 55\nCodec ID/Hint.......: MP3\nBit rate mode.......: Constant\nBitrate.............: 192Kbps\nChannel(s)..........: 2 channels\n\n","torrent":{"xt":"urn:btih:17c6e9ffdab40e2b75b4858dafad51d8b885f229","amp;dn":"All.Cheerleaders.Die.2013.BRRip.XviD.MP3-RARBG","amp;tr":["udp%3A%2F%2Ftracker.openbittorrent.com%3A80","udp%3A%2F%2Fopen.demonii.com%3A1337","udp%3A%2F%2Ftracker.coppersurfer.tk%3A6969","udp%3A%2F%2Fexodus.desync.com%3A6969"],"infoHash":"17c6e9ffdab40e2b75b4858dafad51d8b885f229","infoHashBuffer":{"type":"Buffer","data":[23,198,233,255,218,180,14,43,117,180,133,141,175,173,81,216,184,133,242,41]},"announce":[],"urlList":[]}}