{"title":"La Fille De Monaco 2008 FRENCH DVDRiP XViD NTK","uid":4702367,"size":734083072,"categoryP":"video","categoryS":"movies","magnet":"?xt=urn:btih:524f52170785be471196fbba8296ebd7676ccb1d&amp;dn=La+Fille+De+Monaco+2008+FRENCH+DVDRiP+XViD+NTK&amp;tr=udp%3A%2F%2Ftracker.openbittorrent.com%3A80&amp;tr=udp%3A%2F%2Fopen.demonii.com%3A1337&amp;tr=udp%3A%2F%2Ftracker.coppersurfer.tk%3A6969&amp;tr=udp%3A%2F%2Fexodus.desync.com%3A6969","seeders":3,"leechers":0,"uploader":"sugarlova","files":1,"time":1233758887,"description":"La Fille De Monaco 2008 FRENCH DVDRiP XViD NTK\n\nComÃƒÂ©die dramatique avec Louise Bourgoin et Fabrice Luchini.\n\nDurÃƒÂ©e : 1h30\n\nx-x-x-x-x-x-x-x-x-x-x-x-x-x-x-x-x-x-x-x-x-x-x-x-x-x-x-x-x-x-x-x-x-x-x-x-x-x-x-x-x-x-\n\nAlors que nous sommes en 2009, certains fichiers restent inaccessibles ÃƒÂ  la plupart ÃƒÂ  cause des trackers privÃƒÂ©s.\n\nJe me permets donc de re-uploader ce film pour que tout le monde puisse en profiter. N'oubliez pas de partager :)\n\nEnjoy!","torrent":{"xt":"urn:btih:524f52170785be471196fbba8296ebd7676ccb1d","amp;dn":"La+Fille+De+Monaco+2008+FRENCH+DVDRiP+XViD+NTK","amp;tr":["udp%3A%2F%2Ftracker.openbittorrent.com%3A80","udp%3A%2F%2Fopen.demonii.com%3A1337","udp%3A%2F%2Ftracker.coppersurfer.tk%3A6969","udp%3A%2F%2Fexodus.desync.com%3A6969"],"infoHash":"524f52170785be471196fbba8296ebd7676ccb1d","infoHashBuffer":{"type":"Buffer","data":[82,79,82,23,7,133,190,71,17,150,251,186,130,150,235,215,103,108,203,29]},"announce":[],"urlList":[]}}