{"title":"Our World The Horrors of the Red House 720p HDTV x264-MVGroup","uid":15016316,"size":494670724,"categoryP":"video","categoryS":"hd___tv_shows","magnet":"?xt=urn:btih:5a5e2788c40f4043dd88e8b1c5f4bcdf10efcfe5&amp;dn=Our+World+The+Horrors+of+the+Red+House+720p+HDTV+x264-MVGroup&amp;tr=udp%3A%2F%2Ftracker.leechers-paradise.org%3A6969&amp;tr=udp%3A%2F%2Fzer0day.ch%3A1337&amp;tr=udp%3A%2F%2Fopen.demonii.com%3A1337&amp;tr=udp%3A%2F%2Ftracker.coppersurfer.tk%3A6969&amp;tr=udp%3A%2F%2Fexodus.desync.com%3A6969","seeders":3,"leechers":1,"uploader":"MVGroup","files":1,"time":1466452667,"description":"BBC Our World 2016 The Horrors of the Red House HDTV x264-MVGroup.mkv\r\n\r\nFilipina women who were raped by Japanese soldiers during the Second World War tell their extraordinary stories. The handful of women who are still alive are fighting to make sure their ordeal isn't forgotten and asking for a full state apology from the Japanese Government.\r\n\r\nTechnical Spec\r\nVideo Codec: x264 CABAC   \r\nVideo Bitrate: CRF 20 (~2715Kbps)\r\nVideo Resolution: 1280x656\r\nVideo Aspect Ratio: 1.95:1\r\nFrames Rate: 25 FPS\r\nAudio Codec: AAC-LC\r\nAudio Bitrate: Q=0.48 VBR 48KHz (~125Kbps)\r\nAudio Channels: 2\r\nRun-Time: 23 mins\r\nNumber Of Parts: 1\r\nPart Size: 472 MB\r\nSource: HDTV\r\nSubtitles: Merged","torrent":{"xt":"urn:btih:5a5e2788c40f4043dd88e8b1c5f4bcdf10efcfe5","amp;dn":"Our+World+The+Horrors+of+the+Red+House+720p+HDTV+x264-MVGroup","amp;tr":["udp%3A%2F%2Ftracker.leechers-paradise.org%3A6969","udp%3A%2F%2Fzer0day.ch%3A1337","udp%3A%2F%2Fopen.demonii.com%3A1337","udp%3A%2F%2Ftracker.coppersurfer.tk%3A6969","udp%3A%2F%2Fexodus.desync.com%3A6969"],"infoHash":"5a5e2788c40f4043dd88e8b1c5f4bcdf10efcfe5","infoHashBuffer":{"type":"Buffer","data":[90,94,39,136,196,15,64,67,221,136,232,177,197,244,188,223,16,239,207,229]},"announce":[],"urlList":[]}}