{"title":"3XL White Table Top Booty (Evasive Angles) XXX DVDRip NEW (2014)","uid":9571690,"size":1820543693,"categoryP":"porn","categoryS":"movies","magnet":"?xt=urn:btih:5a77170715bdfc7bb9a4fa399a1144ee599255c3&amp;dn=3XL+White+Table+Top+Booty+%28Evasive+Angles%29+XXX+DVDRip+NEW+%282014%29&amp;tr=udp%3A%2F%2Ftracker.openbittorrent.com%3A80&amp;tr=udp%3A%2F%2Fopen.demonii.com%3A1337&amp;tr=udp%3A%2F%2Ftracker.coppersurfer.tk%3A6969&amp;tr=udp%3A%2F%2Fexodus.desync.com%3A6969","seeders":3,"leechers":10,"uploader":"xuluhulu","files":1,"time":1391640284,"description":"What is PAWG we are putting down Today and phat white Asses These are big Real Real big! Cover girl Felicia Clover is one of the sultry horny redheads. She is a beauty young and dripping wet for a big dick and has natural triple D breasts and a 50 in. ass! Felicia can't get enough sex and truly enjoys getting her pussy fucked hard! Mazzaratie has the biggest ass in the flick and Wesley has his hands full as she has a 60 inch butt! It's insane and she is a real woman who can fuck your brains out! Then we have the most beautiful round ass blonde Alexis Love who is almost perfect and has the bombest pussy ever! Plus wild Vanessa.\n\nCOVERS:\n &lt;a href=&quot;\nhttp://imghoney.com/viewer.php?file=40556271685730052901.jpg&quot; rel=&quot;nofollow&quot; target=&quot;_NEW&quot;&gt;\nhttp://imghoney.com/viewer.php?file=40556271685730052901.jpg&lt;/a&gt;\n\n\nTHUMBSNAIL SCREENS:\n &lt;a href=&quot;\nhttp://imghoney.com/viewer.php?file=50033725334462362354.jpg&quot; rel=&quot;nofollow&quot; target=&quot;_NEW&quot;&gt;\nhttp://imghoney.com/viewer.php?file=50033725334462362354.jpg&lt;/a&gt;\n\n\nCAST:\n\nFelicia Clover, Alexis Love, Mazzaratie Monica, Vanessa Blake / J. Strokes, Wesley Pipes, Charlie Mac.\n\n\nSEED &amp; ENJOY!!!","torrent":{"xt":"urn:btih:5a77170715bdfc7bb9a4fa399a1144ee599255c3","amp;dn":"3XL+White+Table+Top+Booty+%28Evasive+Angles%29+XXX+DVDRip+NEW+%282014%29","amp;tr":["udp%3A%2F%2Ftracker.openbittorrent.com%3A80","udp%3A%2F%2Fopen.demonii.com%3A1337","udp%3A%2F%2Ftracker.coppersurfer.tk%3A6969","udp%3A%2F%2Fexodus.desync.com%3A6969"],"infoHash":"5a77170715bdfc7bb9a4fa399a1144ee599255c3","infoHashBuffer":{"type":"Buffer","data":[90,119,23,7,21,189,252,123,185,164,250,57,154,17,68,238,89,146,85,195]},"announce":[],"urlList":[]}}