{"title":"Rick Steves Prague &amp; The Czech Republic - by Rick Steves - m","uid":7506302,"size":6056946,"categoryP":"other","categoryS":"e_books","magnet":"?xt=urn:btih:6893fccb00758152643f42c385aad9bd18e0c0f7&amp;dn=Rick+Steves+Prague+%26amp%3B+The+Czech+Republic+-+by+Rick+Steves+-+m&amp;tr=udp%3A%2F%2Ftracker.openbittorrent.com%3A80&amp;tr=udp%3A%2F%2Fopen.demonii.com%3A1337&amp;tr=udp%3A%2F%2Ftracker.coppersurfer.tk%3A6969&amp;tr=udp%3A%2F%2Fexodus.desync.com%3A6969","seeders":3,"leechers":0,"uploader":"ebooklover7","files":2,"time":1344185124,"description":"Rick Steves Prague &amp; The Czech Republic - by Rick Steves - mobi ebook","torrent":{"xt":"urn:btih:6893fccb00758152643f42c385aad9bd18e0c0f7","amp;dn":"Rick+Steves+Prague+%26amp%3B+The+Czech+Republic+-+by+Rick+Steves+-+m","amp;tr":["udp%3A%2F%2Ftracker.openbittorrent.com%3A80","udp%3A%2F%2Fopen.demonii.com%3A1337","udp%3A%2F%2Ftracker.coppersurfer.tk%3A6969","udp%3A%2F%2Fexodus.desync.com%3A6969"],"infoHash":"6893fccb00758152643f42c385aad9bd18e0c0f7","infoHashBuffer":{"type":"Buffer","data":[104,147,252,203,0,117,129,82,100,63,66,195,133,170,217,189,24,224,192,247]},"announce":[],"urlList":[]}}