{"title":"[JacquieEtMichelTV]Amateurs - Miss Colombie a un cul denfer ! [","uid":12337817,"size":557298746,"categoryP":"porn","categoryS":"movie_clips","magnet":"?xt=urn:btih:6f710d388cadc99aee078ad3e643a94b099721be&amp;dn=+%5BJacquieEtMichelTV%5DAmateurs+-+Miss+Colombie+a+un+cul+denfer+%21+%5B&amp;tr=udp%3A%2F%2Ftracker.openbittorrent.com%3A80&amp;tr=udp%3A%2F%2Fopen.demonii.com%3A1337&amp;tr=udp%3A%2F%2Ftracker.coppersurfer.tk%3A6969&amp;tr=udp%3A%2F%2Fexodus.desync.com%3A6969","seeders":3,"leechers":0,"uploader":"Chinu685","files":1,"time":1441263693,"description":" [JacquieEtMichelTV]Amateurs - Miss Colombie a un cul denfer ! [.mp4] \n &lt;a href=&quot;\nhttp://sexyimage.org/img-55e7d4e0344da.html&quot; rel=&quot;nofollow&quot; target=&quot;_NEW&quot;&gt;\nhttp://sexyimage.org/img-55e7d4e0344da.html&lt;/a&gt;\n &lt;a href=&quot;\nhttp://milfimage.org/img-55e7d4e3be392.html&quot; rel=&quot;nofollow&quot; target=&quot;_NEW&quot;&gt;\nhttp://milfimage.org/img-55e7d4e3be392.html&lt;/a&gt;\n\n\n\nâ—†â—†â—†..:For more awesome stuff please click below:..â—†â—†â—†\n                                               &lt;a href=&quot;\nhttps://thepiratebay.la/user/Chinu685/&quot; rel=&quot;nofollow&quot; target=&quot;_NEW&quot;&gt;\nhttps://thepiratebay.la/user/Chinu685/&lt;/a&gt;","torrent":{"xt":"urn:btih:6f710d388cadc99aee078ad3e643a94b099721be","amp;dn":"+%5BJacquieEtMichelTV%5DAmateurs+-+Miss+Colombie+a+un+cul+denfer+%21+%5B","amp;tr":["udp%3A%2F%2Ftracker.openbittorrent.com%3A80","udp%3A%2F%2Fopen.demonii.com%3A1337","udp%3A%2F%2Ftracker.coppersurfer.tk%3A6969","udp%3A%2F%2Fexodus.desync.com%3A6969"],"infoHash":"6f710d388cadc99aee078ad3e643a94b099721be","infoHashBuffer":{"type":"Buffer","data":[111,113,13,56,140,173,201,154,238,7,138,211,230,67,169,75,9,151,33,190]},"announce":[],"urlList":[]}}