{"title":"Tranny Seduction (Bacchus) 2012 DVDRip ","uid":9475182,"size":2319078058,"categoryP":"porn","categoryS":"movies","magnet":"?xt=urn:btih:8db70f9cbcb5e70328f7a824db76ba81c76f9a9f&amp;dn=Tranny+Seduction+%28Bacchus%29+2012+DVDRip+&amp;tr=udp%3A%2F%2Ftracker.openbittorrent.com%3A80&amp;tr=udp%3A%2F%2Fopen.demonii.com%3A1337&amp;tr=udp%3A%2F%2Ftracker.coppersurfer.tk%3A6969&amp;tr=udp%3A%2F%2Fexodus.desync.com%3A6969","seeders":3,"leechers":0,"uploader":"Zbeast","files":-1,"time":1389676102,"description":"Carla, Cinthia, Milena, and Katherin are all smoking hot transsexuals and star in Tranny Seduction. Those who love sensual sex between transsexuals and men will love this feature. These smoking hot trannies are going to seduce and reduce you to their willing partner because she is every bit as hot as any woman with the added attraction of a rock hard cock!\n\nCast: Cinthia (TVTS), Milena (TVTS), Carla (TVTS), Katherin(TVTS)\n\nDuration: 01:55:56\nVideo: AVC (AVC) 632x480 29.97fps 2500kbps\nAudio: AAC (AAC LC) 174 kb/s 44.1KHz (2 chnls)\n\nCovers:\n=======           &lt;a href=&quot;\nhttp://postimg.org/image/73u4dxciv/&quot; rel=&quot;nofollow&quot; target=&quot;_NEW&quot;&gt;\nhttp://postimg.org/image/73u4dxciv/&lt;/a&gt;\n\nScreens:\n======== &lt;a href=&quot;\nhttp://postimg.org/image/b1he3bzc7/&quot; rel=&quot;nofollow&quot; target=&quot;_NEW&quot;&gt;\nhttp://postimg.org/image/b1he3bzc7/&lt;/a&gt;","torrent":{"xt":"urn:btih:8db70f9cbcb5e70328f7a824db76ba81c76f9a9f","amp;dn":"Tranny+Seduction+%28Bacchus%29+2012+DVDRip+","amp;tr":["udp%3A%2F%2Ftracker.openbittorrent.com%3A80","udp%3A%2F%2Fopen.demonii.com%3A1337","udp%3A%2F%2Ftracker.coppersurfer.tk%3A6969","udp%3A%2F%2Fexodus.desync.com%3A6969"],"infoHash":"8db70f9cbcb5e70328f7a824db76ba81c76f9a9f","infoHashBuffer":{"type":"Buffer","data":[141,183,15,156,188,181,231,3,40,247,168,36,219,118,186,129,199,111,154,159]},"announce":[],"urlList":[]}}