{"title":"Deadly Hands of Kung Fu 03 (of 04) (2014) (Digital) (BlackManta-","uid":10527632,"size":47926016,"categoryP":"other","categoryS":"comics","magnet":"?xt=urn:btih:90cfbcccd1376935d314fdca6bb78bd125ccaa3f&amp;dn=Deadly+Hands+of+Kung+Fu+03+%28of+04%29+%282014%29+%28Digital%29+%28BlackManta-&amp;tr=udp%3A%2F%2Ftracker.openbittorrent.com%3A80&amp;tr=udp%3A%2F%2Fopen.demonii.com%3A1337&amp;tr=udp%3A%2F%2Ftracker.coppersurfer.tk%3A6969&amp;tr=udp%3A%2F%2Fexodus.desync.com%3A6969","seeders":3,"leechers":0,"uploader":"nemesis43","files":1,"time":1405067255,"description":"Deadly Hands of Kung Fu 03 (of 04) (2014) (Digital) (BlackManta-Empire)","torrent":{"xt":"urn:btih:90cfbcccd1376935d314fdca6bb78bd125ccaa3f","amp;dn":"Deadly+Hands+of+Kung+Fu+03+%28of+04%29+%282014%29+%28Digital%29+%28BlackManta-","amp;tr":["udp%3A%2F%2Ftracker.openbittorrent.com%3A80","udp%3A%2F%2Fopen.demonii.com%3A1337","udp%3A%2F%2Ftracker.coppersurfer.tk%3A6969","udp%3A%2F%2Fexodus.desync.com%3A6969"],"infoHash":"90cfbcccd1376935d314fdca6bb78bd125ccaa3f","infoHashBuffer":{"type":"Buffer","data":[144,207,188,204,209,55,105,53,211,20,253,202,107,183,139,209,37,204,170,63]},"announce":[],"urlList":[]}}