{"title":"Frank Sinatra - The Sinatra Christmas Album [2004] pctorren","uid":3262111,"size":55781451,"categoryP":"audio","categoryS":"music","magnet":"?xt=urn:btih:92451089bd1c50c61c781dfbd31d01dbb317472b&amp;dn=Frank+Sinatra+-+The+Sinatra+Christmas+Album+%5B2004%5D+pctorren&amp;tr=udp%3A%2F%2Ftracker.openbittorrent.com%3A80&amp;tr=udp%3A%2F%2Fopen.demonii.com%3A1337&amp;tr=udp%3A%2F%2Ftracker.coppersurfer.tk%3A6969&amp;tr=udp%3A%2F%2Fexodus.desync.com%3A6969","seeders":3,"leechers":0,"uploader":"pctorrent","files":18,"time":1102266720,"description":"Visit www.pctorrent.com !!!","torrent":{"xt":"urn:btih:92451089bd1c50c61c781dfbd31d01dbb317472b","amp;dn":"Frank+Sinatra+-+The+Sinatra+Christmas+Album+%5B2004%5D+pctorren","amp;tr":["udp%3A%2F%2Ftracker.openbittorrent.com%3A80","udp%3A%2F%2Fopen.demonii.com%3A1337","udp%3A%2F%2Ftracker.coppersurfer.tk%3A6969","udp%3A%2F%2Fexodus.desync.com%3A6969"],"infoHash":"92451089bd1c50c61c781dfbd31d01dbb317472b","infoHashBuffer":{"type":"Buffer","data":[146,69,16,137,189,28,80,198,28,120,29,251,211,29,1,219,179,23,71,43]},"announce":[],"urlList":[]}}