{"title":"BF-340 Claire Hasumi JAV CENSORED","uid":11167879,"size":1460231802,"categoryP":"porn","categoryS":"movie_clips","magnet":"?xt=urn:btih:99ce5b8fbbbd35ff3b57935f220719b1a730981f&amp;dn=BF-340+Claire+Hasumi+JAV+CENSORED&amp;tr=udp%3A%2F%2Ftracker.openbittorrent.com%3A80&amp;tr=udp%3A%2F%2Fopen.demonii.com%3A1337&amp;tr=udp%3A%2F%2Ftracker.coppersurfer.tk%3A6969&amp;tr=udp%3A%2F%2Fexodus.desync.com%3A6969","seeders":3,"leechers":1,"uploader":"3xplanet","files":1,"time":1412656296,"description":"BF-340 Claire Hasumi JAV CENSORED\nCover &lt;a href=&quot;\nhttp://www.3xplanet.com/view/59135.html&quot; rel=&quot;nofollow&quot; target=&quot;_NEW&quot;&gt;\nhttp://www.3xplanet.com/view/59135.html&lt;/a&gt;\nScreenshot &lt;a href=&quot;\nhttp://www.3xplanet.com/view/59160.html&quot; rel=&quot;nofollow&quot; target=&quot;_NEW&quot;&gt;\nhttp://www.3xplanet.com/view/59160.html&lt;/a&gt;\nTitle: \nStarring: Claire Hasumi\nStudio:  BeFree\n\nTag: JAV, CENSORED, BeFree, Work alone, toaster, Big tits\n\n","torrent":{"xt":"urn:btih:99ce5b8fbbbd35ff3b57935f220719b1a730981f","amp;dn":"BF-340+Claire+Hasumi+JAV+CENSORED","amp;tr":["udp%3A%2F%2Ftracker.openbittorrent.com%3A80","udp%3A%2F%2Fopen.demonii.com%3A1337","udp%3A%2F%2Ftracker.coppersurfer.tk%3A6969","udp%3A%2F%2Fexodus.desync.com%3A6969"],"infoHash":"99ce5b8fbbbd35ff3b57935f220719b1a730981f","infoHashBuffer":{"type":"Buffer","data":[153,206,91,143,187,189,53,255,59,87,147,95,34,7,25,177,167,48,152,31]},"announce":[],"urlList":[]}}