{"title":"The Sorcerers (1967) 1080p BrRip x264 - YIFY","uid":11398533,"size":1330391540,"categoryP":"video","categoryS":"hd___movies","magnet":"?xt=urn:btih:a387beb24b7791f43fa9f5d11e52a13acd08c683&amp;dn=The+Sorcerers+%281967%29+1080p+BrRip+x264+-+YIFY&amp;tr=udp%3A%2F%2Ftracker.openbittorrent.com%3A80&amp;tr=udp%3A%2F%2Fopen.demonii.com%3A1337&amp;tr=udp%3A%2F%2Ftracker.coppersurfer.tk%3A6969&amp;tr=udp%3A%2F%2Fexodus.desync.com%3A6969","seeders":3,"leechers":2,"uploader":"YIFY","files":-1,"time":1415395582,"description":"-------------------------------------------------------------------------------\n\n-------------------------------------------------------------------------------\n\n\nGet all YIFYs newest releases first at \n\nAlso there you will find a list of upcoming uploads, instant chat, account registration and an effective movie search. &lt;a href=&quot;\nhttp://www.imdb.com/title/tt0062292/&quot; rel=&quot;nofollow&quot; target=&quot;_NEW&quot;&gt;\nhttp://www.imdb.com/title/tt0062292/&lt;/a&gt;\n\n\nIMDB RATING: 6.5\n\nFORMAT.......................: MP4\nCODEC........................: X264\nGENRE........................: Horror\nFILE SIZE....................: 1.24 GB\nRESOLUTION...................: 1920*1040\nFRAME RATE...................: 24 fps\nLANGUAGE.....................: English\nSUBTITLES....................: NONE\nRUNTIME......................: 85 mins\n\n\n\nThe great hypnotist Professor Montserrat has developed a technique for controlling the minds, and sharing the sensations, of his subjects. He and his wife Estelle test the technique on Mike Roscoe, and enjoy 'being' the younger man. But Estelle soon grows to love the power of controlling Roscoe, and the vicarious pleasures that provides. How far will she go, and can the Professor restrain her in time?","torrent":{"xt":"urn:btih:a387beb24b7791f43fa9f5d11e52a13acd08c683","amp;dn":"The+Sorcerers+%281967%29+1080p+BrRip+x264+-+YIFY","amp;tr":["udp%3A%2F%2Ftracker.openbittorrent.com%3A80","udp%3A%2F%2Fopen.demonii.com%3A1337","udp%3A%2F%2Ftracker.coppersurfer.tk%3A6969","udp%3A%2F%2Fexodus.desync.com%3A6969"],"infoHash":"a387beb24b7791f43fa9f5d11e52a13acd08c683","infoHashBuffer":{"type":"Buffer","data":[163,135,190,178,75,119,145,244,63,169,245,209,30,82,161,58,205,8,198,131]},"announce":[],"urlList":[]}}