{"title":"Stephen King - Carrie (1974) - epub mobi pdf","uid":8867711,"size":5172903,"categoryP":"other","categoryS":"e_books","magnet":"?xt=urn:btih:a3b35ce310c3e78a3f9495ec8b57317f04c25360&amp;dn=Stephen+King+-+Carrie+%281974%29+-+epub+mobi+pdf&amp;tr=udp%3A%2F%2Ftracker.openbittorrent.com%3A80&amp;tr=udp%3A%2F%2Fopen.demonii.com%3A1337&amp;tr=udp%3A%2F%2Ftracker.coppersurfer.tk%3A6969&amp;tr=udp%3A%2F%2Fexodus.desync.com%3A6969","seeders":3,"leechers":0,"uploader":"sitapea1","files":9,"time":1377968851,"description":"For offline download, there's file named &quot;j.mp&quot;, replace &quot;- &quot; with &quot;/&quot; and you got the link :)\n\n\nj.mp- CQcDfLjhr4G3KTQuPgQPdEzp","torrent":{"xt":"urn:btih:a3b35ce310c3e78a3f9495ec8b57317f04c25360","amp;dn":"Stephen+King+-+Carrie+%281974%29+-+epub+mobi+pdf","amp;tr":["udp%3A%2F%2Ftracker.openbittorrent.com%3A80","udp%3A%2F%2Fopen.demonii.com%3A1337","udp%3A%2F%2Ftracker.coppersurfer.tk%3A6969","udp%3A%2F%2Fexodus.desync.com%3A6969"],"infoHash":"a3b35ce310c3e78a3f9495ec8b57317f04c25360","infoHashBuffer":{"type":"Buffer","data":[163,179,92,227,16,195,231,138,63,148,149,236,139,87,49,127,4,194,83,96]},"announce":[],"urlList":[]}}