{"title":"Dirty Milf Club - Darryl Hanah (Dirty MILF Darryl Hanah)","uid":11671970,"size":467153372,"categoryP":"porn","categoryS":"movie_clips","magnet":"?xt=urn:btih:a8b933678f16d9e1f58a3a38a59ea67a9a6959f7&amp;dn=Dirty+Milf+Club+-+Darryl+Hanah+%28Dirty+MILF+Darryl+Hanah%29&amp;tr=udp%3A%2F%2Ftracker.openbittorrent.com%3A80&amp;tr=udp%3A%2F%2Fopen.demonii.com%3A1337&amp;tr=udp%3A%2F%2Ftracker.coppersurfer.tk%3A6969&amp;tr=udp%3A%2F%2Fexodus.desync.com%3A6969","seeders":3,"leechers":0,"uploader":"Upl0ad3rR","files":1,"time":1422728304,"description":"---:More From My Torrent's Here:---  &lt;a href=&quot;\nhttps://thepiratebay.se/user/Upl0ad3rR&quot; rel=&quot;nofollow&quot; target=&quot;_NEW&quot;&gt;\nhttps://thepiratebay.se/user/Upl0ad3rR&lt;/a&gt;\n\n---:ScreeNshotS:---  &lt;a href=&quot;\nhttp://image-tpb.com/img-54cd0e315cebe.html&quot; rel=&quot;nofollow&quot; target=&quot;_NEW&quot;&gt;\nhttp://image-tpb.com/img-54cd0e315cebe.html&lt;/a&gt;  &lt;a href=&quot;\nhttp://image-tpb.com/img-54cd0e32ebe11.html&quot; rel=&quot;nofollow&quot; target=&quot;_NEW&quot;&gt;\nhttp://image-tpb.com/img-54cd0e32ebe11.html&lt;/a&gt; \n\nJust like her Hollywood alterego, Darryl is a glamorous lady, but there's something missing from her life. The 44-year-old beauty is desperate to have kids - now she is in search of the perfect father... Cum on in, you have the be the best!","torrent":{"xt":"urn:btih:a8b933678f16d9e1f58a3a38a59ea67a9a6959f7","amp;dn":"Dirty+Milf+Club+-+Darryl+Hanah+%28Dirty+MILF+Darryl+Hanah%29","amp;tr":["udp%3A%2F%2Ftracker.openbittorrent.com%3A80","udp%3A%2F%2Fopen.demonii.com%3A1337","udp%3A%2F%2Ftracker.coppersurfer.tk%3A6969","udp%3A%2F%2Fexodus.desync.com%3A6969"],"infoHash":"a8b933678f16d9e1f58a3a38a59ea67a9a6959f7","infoHashBuffer":{"type":"Buffer","data":[168,185,51,103,143,22,217,225,245,138,58,56,165,158,166,122,154,105,89,247]},"announce":[],"urlList":[]}}