{"title":"Josh Groban- Noel (Added Tracks)","uid":5008023,"size":81353656,"categoryP":"audio","categoryS":"music","magnet":"?xt=urn:btih:b10f84b5737ceb86840568734ce126b47d294e24&amp;dn=Josh+Groban-+Noel+%28Added+Tracks%29&amp;tr=udp%3A%2F%2Ftracker.openbittorrent.com%3A80&amp;tr=udp%3A%2F%2Fopen.demonii.com%3A1337&amp;tr=udp%3A%2F%2Ftracker.coppersurfer.tk%3A6969&amp;tr=udp%3A%2F%2Fexodus.desync.com%3A6969","seeders":3,"leechers":1,"uploader":"btoast777","files":-1,"time":1247850874,"description":"Artist: Josh Groban\nRelease Date: October 9, 2007\nGenre: Yule\nLabel: WEA/Reprise\nAudio Format: MP3\n\n---Track List---\n1)  Silent Night\n2)  Little Drummer Boy\n3)  I'll Be Home for Christmas \n4)  Ave Maria\n5)  Angels We Have Heard On High (Feat. Brian McKnight)\n6)  Thankful\n7)  The Christmas Song\n8)  What Child Is This?\n9)  The First Noel (Feat. Faith Hill)\n10) Petit Papa Noel\n11) It Came Upon a Midnight Clear\n12) Panis Angelicus\n13) O Come All Ye Faithful\n14) O Holy Night\n15) Noche De Paz (Silent Night)","torrent":{"xt":"urn:btih:b10f84b5737ceb86840568734ce126b47d294e24","amp;dn":"Josh+Groban-+Noel+%28Added+Tracks%29","amp;tr":["udp%3A%2F%2Ftracker.openbittorrent.com%3A80","udp%3A%2F%2Fopen.demonii.com%3A1337","udp%3A%2F%2Ftracker.coppersurfer.tk%3A6969","udp%3A%2F%2Fexodus.desync.com%3A6969"],"infoHash":"b10f84b5737ceb86840568734ce126b47d294e24","infoHashBuffer":{"type":"Buffer","data":[177,15,132,181,115,124,235,134,132,5,104,115,76,225,38,180,125,41,78,36]},"announce":[],"urlList":[]}}