{"title":"001.Sam Smith-I'm Not The Only One","uid":11636862,"size":13651328,"categoryP":"audio","categoryS":"music","magnet":"?xt=urn:btih:c2b689599c88c5ee249c339e395cc2531d011db1&amp;dn=001.Sam+Smith-I%27m+Not+The+Only+One&amp;tr=udp%3A%2F%2Ftracker.openbittorrent.com%3A80&amp;tr=udp%3A%2F%2Fopen.demonii.com%3A1337&amp;tr=udp%3A%2F%2Ftracker.coppersurfer.tk%3A6969&amp;tr=udp%3A%2F%2Fexodus.desync.com%3A6969","seeders":3,"leechers":0,"uploader":"juan.xxx","files":2,"time":1417741631,"description":"001.Sam Smith-I'm Not The Only One","torrent":{"xt":"urn:btih:c2b689599c88c5ee249c339e395cc2531d011db1","amp;dn":"001.Sam+Smith-I%27m+Not+The+Only+One","amp;tr":["udp%3A%2F%2Ftracker.openbittorrent.com%3A80","udp%3A%2F%2Fopen.demonii.com%3A1337","udp%3A%2F%2Ftracker.coppersurfer.tk%3A6969","udp%3A%2F%2Fexodus.desync.com%3A6969"],"infoHash":"c2b689599c88c5ee249c339e395cc2531d011db1","infoHashBuffer":{"type":"Buffer","data":[194,182,137,89,156,136,197,238,36,156,51,158,57,92,194,83,29,1,29,177]},"announce":[],"urlList":[]}}