{"title":"BBC.Glastonbury.2014.Day2.Red.Button.576i.mpeg2-NX","uid":10451080,"size":25944594268,"categoryP":"video","categoryS":"tv_shows","magnet":"?xt=urn:btih:e3b6c311a3f37bf1d79ae2d65257d4e1f7b517d0&amp;dn=BBC.Glastonbury.2014.Day2.Red.Button.576i.mpeg2-NX&amp;tr=udp%3A%2F%2Ftracker.openbittorrent.com%3A80&amp;tr=udp%3A%2F%2Fopen.demonii.com%3A1337&amp;tr=udp%3A%2F%2Ftracker.coppersurfer.tk%3A6969&amp;tr=udp%3A%2F%2Fexodus.desync.com%3A6969","seeders":3,"leechers":0,"uploader":"BasilBrush","files":-1,"time":1404018955,"description":"BBC.Glastonbury.2014.Day2.Red.Button.576i.mpeg2-NX\n\nSaturday 28th June 2014 Red Button\n21:00 to 02:00 Red Button 1\n21:00 to 02:00 Red Button 2\n21:00 to 02:00 Red Button 3\n\nMusic from six stages: Pyramid, Other, John Peel, West Holts, Park and BBC Introducing. Welcome to the second day of the festival.\n\nTechnical Spec\nFilesize__: 24.1 GB total\nRun-Time__: 14h 09m total\nContainer_: TS\nVideo_____: mpeg2 Main 720x576i 25fps\nAudio_____: MP2 CBR 2ch 48KHz 128Kbps\n\ndb.tt/IG9eFdTy\ntwitter[dot]com/JungleBoyNX\n","torrent":{"xt":"urn:btih:e3b6c311a3f37bf1d79ae2d65257d4e1f7b517d0","amp;dn":"BBC.Glastonbury.2014.Day2.Red.Button.576i.mpeg2-NX","amp;tr":["udp%3A%2F%2Ftracker.openbittorrent.com%3A80","udp%3A%2F%2Fopen.demonii.com%3A1337","udp%3A%2F%2Ftracker.coppersurfer.tk%3A6969","udp%3A%2F%2Fexodus.desync.com%3A6969"],"infoHash":"e3b6c311a3f37bf1d79ae2d65257d4e1f7b517d0","infoHashBuffer":{"type":"Buffer","data":[227,182,195,17,163,243,123,241,215,154,226,214,82,87,212,225,247,181,23,208]},"announce":[],"urlList":[]}}