{"title":"AUTODESK AutoCAD 2010 English 64bit W/ CRACK DeLtASn1p3r","uid":8921464,"size":1603571186,"categoryP":"applications","categoryS":"windows","magnet":"?xt=urn:btih:f670eb6bb4fb006557509d3761847ff5ffbfef6b&amp;dn=AUTODESK+AutoCAD+2010+English+64bit+W%2F+CRACK+DeLtASn1p3r&amp;tr=udp%3A%2F%2Ftracker.openbittorrent.com%3A80&amp;tr=udp%3A%2F%2Fopen.demonii.com%3A1337&amp;tr=udp%3A%2F%2Ftracker.coppersurfer.tk%3A6969&amp;tr=udp%3A%2F%2Fexodus.desync.com%3A6969","seeders":3,"leechers":0,"uploader":"DeLtA_Sn1p3r","files":1,"time":1379263524,"description":"AutoCAD 2010 Any Questions Email Me @\n\n\nI Have\n\nOver 1000 - 1080p Movies\n\n20 top rated TV Series\n\n100 Apps Just Message Me\n\nOr Email Me @\n\nAnd Ill Upload ASAP SEED","torrent":{"xt":"urn:btih:f670eb6bb4fb006557509d3761847ff5ffbfef6b","amp;dn":"AUTODESK+AutoCAD+2010+English+64bit+W%2F+CRACK+DeLtASn1p3r","amp;tr":["udp%3A%2F%2Ftracker.openbittorrent.com%3A80","udp%3A%2F%2Fopen.demonii.com%3A1337","udp%3A%2F%2Ftracker.coppersurfer.tk%3A6969","udp%3A%2F%2Fexodus.desync.com%3A6969"],"infoHash":"f670eb6bb4fb006557509d3761847ff5ffbfef6b","infoHashBuffer":{"type":"Buffer","data":[246,112,235,107,180,251,0,101,87,80,157,55,97,132,127,245,255,191,239,107]},"announce":[],"urlList":[]}}